getTime.py
get_class_subject.py
get_class_subject-1.0.0.dist-info/METADATA
get_class_subject-1.0.0.dist-info/WHEEL
get_class_subject-1.0.0.dist-info/top_level.txt
get_class_subject-1.0.0.dist-info/RECORD
