Metadata-Version: 2.1
Name: get-class-subject
Version: 1.0.0
Summary: get school subject
Home-page: UNKNOWN
Author: darrime
Author-email: UNKNOWN
License: UNKNOWN
Platform: UNKNOWN
Requires-Dist: selenium
